edge_distance_aabb.cpython-39-i386-linux-gnu.so
edge_distance_aabb-1.0.1.dist-info/RECORD
edge_distance_aabb-1.0.1.dist-info/METADATA
edge_distance_aabb-1.0.1.dist-info/LICENSE
edge_distance_aabb-1.0.1.dist-info/top_level.txt
edge_distance_aabb-1.0.1.dist-info/WHEEL
