Metadata-Version: 2.1
Name: edge-distance-aabb
Version: 1.0.1
Summary: Relatively efficient distance and closest point from a set of points to a set of line segments.
Author-email: Yotam Gingold <yotam@yotamgingold.com>
Project-URL: Homepage, https://github.com/pypa/sampleproject
Project-URL: Bug Tracker, https://github.com/pypa/sampleproject/issues
Classifier: Programming Language :: Python :: 3
Classifier: License :: CC0 1.0 Universal (CC0 1.0) Public Domain Dedication
Classifier: Operating System :: OS Independent
Requires-Python: >=3.5
License-File: LICENSE
